_clone
_eventfd_c
_fanotify_c
_inotify_c
_memfd_c
_signalfd_c
_splice_c
_system_c
_timerfd_c
_utils_c
butter
butter/asyncio
butter/build
