Metadata-Version: 2.1
Name: butter
Version: 0.13.1
Summary: Library to interface to low level linux features (inotify, fanotify, timerfd, signalfd, eventfd, containers) with asyncio support
Home-page: http://blitz.works/butter/file/tip
Author: Da_Blitz
Author-email: code@pocketnix.org
License: MIT BSD
Download-URL: http://blitz.works/butter/archive/tip.tar.bz2
Keywords: linux splice tee fanotify inotify eventfd signalfd timerfd aio clone unshare asyncio container server async
Platform: UNKNOWN
Classifier: Programming Language :: Python :: 3
Classifier: License :: OSI Approved :: BSD License
Classifier: Operating System :: POSIX :: Linux
Classifier: Programming Language :: Python :: 3.4
Classifier: Programming Language :: Python :: 2.7
Classifier: Programming Language :: Python :: Implementation :: PyPy
Classifier: Topic :: Software Development :: Libraries :: Python Modules
Classifier: Topic :: System :: Monitoring
Classifier: Topic :: System :: Systems Administration
Classifier: Development Status :: 5 - Production/Stable
Classifier: Intended Audience :: System Administrators
Classifier: Intended Audience :: Developers
License-File: LICENSE
